beepper/__init__.py
beepper/__init__.pyi
beepper/beepper.py
beepper/beepper.pyi
beepper/generate_wav.py
beepper/generate_wav.pyi
beepper-1.1.2.dist-info/licenses/LICENSE
beepper-1.1.2.dist-info/METADATA
beepper-1.1.2.dist-info/WHEEL
beepper-1.1.2.dist-info/top_level.txt
beepper-1.1.2.dist-info/RECORD
