Metadata-Version: 2.4
Name: beepper
Version: 1.1.2
Summary: Makes an alert noise
Author-email: Henrik Koski <henrikkoski00@gmail.com>
License: Copyright © 2025 PiispaH
Requires-Python: >=3.10
License-File: LICENSE
Requires-Dist: simpleaudio
Requires-Dist: numpy
Dynamic: license-file
